{
  "fields": [
    {
      "aggregatable": true,
      "custom": false,
      "defaultValue": null,
      "extraTypeInfo": null,
      "filterable": true,
      "groupable": true,
      "inlineHelpText": null,
      "label": "Product ID",
      "name": "Id",
      "nillable": false,
      "picklistValues": [],
      "referenceTo": [],
      "relationshipName": null,
      "sortable": true,
      "type": "id"
    },
    {
      "aggregatable": true,
      "custom": false,
      "defaultValue": null,
      "extraTypeInfo": null,
      "filterable": true,
      "groupable": true,
      "inlineHelpText": null,
      "label": "Product Name",
      "name": "Name",
      "nillable": false,
      "picklistValues": [],
      "referenceTo": [],
      "relationshipName": null,
      "sortable": true,
      "type": "string"
    },
    {
      "aggregatable": true,
      "custom": false,
      "defaultValue": null,
      "extraTypeInfo": null,
      "filterable": true,
      "groupable": true,
      "inlineHelpText": null,
      "label": "Product Code",
      "name": "ProductCode",
      "nillable": true,
      "picklistValues": [],
      "referenceTo": [],
      "relationshipName": null,
      "sortable": true,
      "type": "string"
    },
    {
      "aggregatable": true,
      "custom": false,
      "defaultValue": null,
      "extraTypeInfo": "plaintextarea",
      "filterable": true,
      "groupable": false,
      "inlineHelpText": null,
      "label": "Product Description",
      "name": "Description",
      "nillable": true,
      "picklistValues": [],
      "referenceTo": [],
      "relationshipName": null,
      "sortable": true,
      "type": "textarea"
    },
    {
      "aggregatable": true,
      "custom": false,
      "defaultValue": null,
      "extraTypeInfo": null,
      "filterable": true,
      "groupable": true,
      "inlineHelpText": null,
      "label": "Quantity Schedule Type",
      "name": "QuantityScheduleType",
      "nillable": true,
      "picklistValues": [
        {
          "active": true,
          "defaultValue": false,
          "label": "Divide Amount into multiple installments",
          "validFor": null,
          "value": "Divide"
        },
        {
          "active": true,
          "defaultValue": false,
          "label": "Repeat Amount for each installment",
          "validFor": null,
          "value": "Repeat"
        }
      ],
      "referenceTo": [],
      "relationshipName": null,
      "sortable": true,
      "type": "picklist"
    },
    {
      "aggregatable": true,
      "custom": false,
      "defaultValue": null,
      "extraTypeInfo": null,
      "filterable": true,
      "groupable": true,
      "inlineHelpText": null,
      "label": "Quantity Installment Period",
      "name": "QuantityInstallmentPeriod",
      "nillable": true,
      "picklistValues": [
        {
          "active": true,
          "defaultValue": false,
          "label": "Daily",
          "validFor": null,
          "value": "Daily"
        },
        {
          "active": true,
          "defaultValue": false,
          "label": "Weekly",
          "validFor": null,
          "value": "Weekly"
        },
        {
          "active": true,
          "defaultValue": false,
          "label": "Monthly",
          "validFor": null,
          "value": "Monthly"
        },
        {
          "active": true,
          "defaultValue": false,
          "label": "Quarterly",
          "validFor": null,
          "value": "Quarterly"
        },
        {
          "active": true,
          "defaultValue": false,
          "label": "Yearly",
          "validFor": null,
          "value": "Yearly"
        }
      ],
      "referenceTo": [],
      "relationshipName": null,
      "sortable": true,
      "type": "picklist"
    },
    {
      "aggregatable": true,
      "custom": false,
      "defaultValue": null,
      "extraTypeInfo": null,
      "filterable": true,
      "groupable": true,
      "inlineHelpText": null,
      "label": "Number Of Quantity Installments",
      "name": "NumberOfQuantityInstallments",
      "nillable": true,
      "picklistValues": [],
      "referenceTo": [],
      "relationshipName": null,
      "sortable": true,
      "type": "int"
    },
    {
      "aggregatable": true,
      "custom": false,
      "defaultValue": null,
      "extraTypeInfo": null,
      "filterable": true,
      "groupable": true,
      "inlineHelpText": null,
      "label": "Revenue Schedule Type",
      "name": "RevenueScheduleType",
      "nillable": true,
      "picklistValues": [
        {
          "active": true,
          "defaultValue": false,
          "label": "Divide Amount into multiple installments",
          "validFor": null,
          "value": "Divide"
        },
        {
          "active": true,
          "defaultValue": false,
          "label": "Repeat Amount for each installment",
          "validFor": null,
          "value": "Repeat"
        }
      ],
      "referenceTo": [],
      "relationshipName": null,
      "sortable": true,
      "type": "picklist"
    },
    {
      "aggregatable": true,
      "custom": false,
      "defaultValue": null,
      "extraTypeInfo": null,
      "filterable": true,
      "groupable": true,
      "inlineHelpText": null,
      "label": "Revenue Installment Period",
      "name": "RevenueInstallmentPeriod",
      "nillable": true,
      "picklistValues": [
        {
          "active": true,
          "defaultValue": false,
          "label": "Daily",
          "validFor": null,
          "value": "Daily"
        },
        {
          "active": true,
          "defaultValue": false,
          "label": "Weekly",
          "validFor": null,
          "value": "Weekly"
        },
        {
          "active": true,
          "defaultValue": false,
          "label": "Monthly",
          "validFor": null,
          "value": "Monthly"
        },
        {
          "active": true,
          "defaultValue": false,
          "label": "Quarterly",
          "validFor": null,
          "value": "Quarterly"
        },
        {
          "active": true,
          "defaultValue": false,
          "label": "Yearly",
          "validFor": null,
          "value": "Yearly"
        }
      ],
      "referenceTo": [],
      "relationshipName": null,
      "sortable": true,
      "type": "picklist"
    },
    {
      "aggregatable": true,
      "custom": false,
      "defaultValue": null,
      "extraTypeInfo": null,
      "filterable": true,
      "groupable": true,
      "inlineHelpText": null,
      "label": "Number Of Revenue Installments",
      "name": "NumberOfRevenueInstallments",
      "nillable": true,
      "picklistValues": [],
      "referenceTo": [],
      "relationshipName": null,
      "sortable": true,
      "type": "int"
    },
    {
      "aggregatable": false,
      "custom": false,
      "defaultValue": false,
      "extraTypeInfo": null,
      "filterable": true,
      "groupable": true,
      "inlineHelpText": null,
      "label": "Active",
      "name": "IsActive",
      "nillable": false,
      "picklistValues": [],
      "referenceTo": [],
      "relationshipName": null,
      "sortable": true,
      "type": "boolean"
    },
    {
      "aggregatable": true,
      "custom": false,
      "defaultValue": null,
      "extraTypeInfo": null,
      "filterable": true,
      "groupable": false,
      "inlineHelpText": null,
      "label": "Created Date",
      "name": "CreatedDate",
      "nillable": false,
      "picklistValues": [],
      "referenceTo": [],
      "relationshipName": null,
      "sortable": true,
      "type": "datetime"
    },
    {
      "aggregatable": true,
      "custom": false,
      "defaultValue": null,
      "extraTypeInfo": null,
      "filterable": true,
      "groupable": true,
      "inlineHelpText": null,
      "label": "Created By ID",
      "name": "CreatedById",
      "nillable": false,
      "picklistValues": [],
      "referenceTo": [
        "User"
      ],
      "relationshipName": "CreatedBy",
      "sortable": true,
      "type": "reference"
    },
    {
      "aggregatable": true,
      "custom": false,
      "defaultValue": null,
      "extraTypeInfo": null,
      "filterable": true,
      "groupable": false,
      "inlineHelpText": null,
      "label": "Last Modified Date",
      "name": "LastModifiedDate",
      "nillable": false,
      "picklistValues": [],
      "referenceTo": [],
      "relationshipName": null,
      "sortable": true,
      "type": "datetime"
    },
    {
      "aggregatable": true,
      "custom": false,
      "defaultValue": null,
      "extraTypeInfo": null,
      "filterable": true,
      "groupable": true,
      "inlineHelpText": null,
      "label": "Last Modified By ID",
      "name": "LastModifiedById",
      "nillable": false,
      "picklistValues": [],
      "referenceTo": [
        "User"
      ],
      "relationshipName": "LastModifiedBy",
      "sortable": true,
      "type": "reference"
    },
    {
      "aggregatable": true,
      "custom": false,
      "defaultValue": null,
      "extraTypeInfo": null,
      "filterable": true,
      "groupable": false,
      "inlineHelpText": null,
      "label": "System Modstamp",
      "name": "SystemModstamp",
      "nillable": false,
      "picklistValues": [],
      "referenceTo": [],
      "relationshipName": null,
      "sortable": true,
      "type": "datetime"
    },
    {
      "aggregatable": true,
      "custom": false,
      "defaultValue": null,
      "extraTypeInfo": null,
      "filterable": true,
      "groupable": true,
      "inlineHelpText": null,
      "label": "Product Family",
      "name": "Family",
      "nillable": true,
      "picklistValues": [
        {
          "active": true,
          "defaultValue": false,
          "label": "None",
          "validFor": null,
          "value": "None"
        },
        {
          "active": true,
          "defaultValue": false,
          "label": "Multiplay",
          "validFor": null,
          "value": "Multiplay"
        }
      ],
      "referenceTo": [],
      "relationshipName": null,
      "sortable": true,
      "type": "picklist"
    },
    {
      "aggregatable": false,
      "custom": false,
      "defaultValue": false,
      "extraTypeInfo": null,
      "filterable": true,
      "groupable": true,
      "inlineHelpText": null,
      "label": "Serialized",
      "name": "IsSerialized",
      "nillable": false,
      "picklistValues": [],
      "referenceTo": [],
      "relationshipName": null,
      "sortable": true,
      "type": "boolean"
    },
    {
      "aggregatable": true,
      "custom": false,
      "defaultValue": null,
      "extraTypeInfo": null,
      "filterable": true,
      "groupable": true,
      "inlineHelpText": null,
      "label": "Record Type ID",
      "name": "RecordTypeId",
      "nillable": true,
      "picklistValues": [],
      "referenceTo": [
        "RecordType"
      ],
      "relationshipName": "RecordType",
      "sortable": true,
      "type": "reference"
    },
    {
      "aggregatable": true,
      "custom": false,
      "defaultValue": null,
      "extraTypeInfo": null,
      "filterable": true,
      "groupable": true,
      "inlineHelpText": null,
      "label": "External Data Source ID",
      "name": "ExternalDataSourceId",
      "nillable": true,
      "picklistValues": [],
      "referenceTo": [
        "ExternalDataSource"
      ],
      "relationshipName": null,
      "sortable": true,
      "type": "reference"
    },
    {
      "aggregatable": true,
      "custom": false,
      "defaultValue": null,
      "extraTypeInfo": null,
      "filterable": true,
      "groupable": true,
      "inlineHelpText": null,
      "label": "External ID",
      "name": "ExternalId",
      "nillable": true,
      "picklistValues": [],
      "referenceTo": [],
      "relationshipName": null,
      "sortable": true,
      "type": "string"
    },
    {
      "aggregatable": true,
      "custom": false,
      "defaultValue": null,
      "extraTypeInfo": null,
      "filterable": true,
      "groupable": false,
      "inlineHelpText": null,
      "label": "Display URL",
      "name": "DisplayUrl",
      "nillable": true,
      "picklistValues": [],
      "referenceTo": [],
      "relationshipName": null,
      "sortable": true,
      "type": "url"
    },
    {
      "aggregatable": true,
      "custom": false,
      "defaultValue": null,
      "extraTypeInfo": null,
      "filterable": true,
      "groupable": true,
      "inlineHelpText": null,
      "label": "Quantity Unit Of Measure",
      "name": "QuantityUnitOfMeasure",
      "nillable": true,
      "picklistValues": [
        {
          "active": true,
          "defaultValue": false,
          "label": "Each",
          "validFor": null,
          "value": "Each"
        }
      ],
      "referenceTo": [],
      "relationshipName": null,
      "sortable": true,
      "type": "picklist"
    },
    {
      "aggregatable": false,
      "custom": false,
      "defaultValue": false,
      "extraTypeInfo": null,
      "filterable": true,
      "groupable": true,
      "inlineHelpText": null,
      "label": "Deleted",
      "name": "IsDeleted",
      "nillable": false,
      "picklistValues": [],
      "referenceTo": [],
      "relationshipName": null,
      "sortable": true,
      "type": "boolean"
    },
    {
      "aggregatable": false,
      "custom": false,
      "defaultValue": false,
      "extraTypeInfo": null,
      "filterable": true,
      "groupable": true,
      "inlineHelpText": null,
      "label": "Archived",
      "name": "IsArchived",
      "nillable": false,
      "picklistValues": [],
      "referenceTo": [],
      "relationshipName": null,
      "sortable": true,
      "type": "boolean"
    },
    {
      "aggregatable": true,
      "custom": false,
      "defaultValue": null,
      "extraTypeInfo": null,
      "filterable": true,
      "groupable": false,
      "inlineHelpText": null,
      "label": "Last Viewed Date",
      "name": "LastViewedDate",
      "nillable": true,
      "picklistValues": [],
      "referenceTo": [],
      "relationshipName": null,
      "sortable": true,
      "type": "datetime"
    },
    {
      "aggregatable": true,
      "custom": false,
      "defaultValue": null,
      "extraTypeInfo": null,
      "filterable": true,
      "groupable": false,
      "inlineHelpText": null,
      "label": "Last Referenced Date",
      "name": "LastReferencedDate",
      "nillable": true,
      "picklistValues": [],
      "referenceTo": [],
      "relationshipName": null,
      "sortable": true,
      "type": "datetime"
    },
    {
      "aggregatable": true,
      "custom": false,
      "defaultValue": null,
      "extraTypeInfo": null,
      "filterable": true,
      "groupable": true,
      "inlineHelpText": null,
      "label": "Product SKU",
      "name": "StockKeepingUnit",
      "nillable": true,
      "picklistValues": [],
      "referenceTo": [],
      "relationshipName": null,
      "sortable": true,
      "type": "string"
    },
    {
      "aggregatable": true,
      "custom": true,
      "defaultValue": null,
      "extraTypeInfo": null,
      "filterable": true,
      "groupable": true,
      "inlineHelpText": null,
      "label": "Approved By",
      "name": "vlocity_cmt__ApprovedBy__c",
      "nillable": true,
      "picklistValues": [],
      "referenceTo": [
        "Contact"
      ],
      "relationshipName": "vlocity_cmt__ApprovedBy__r",
      "sortable": true,
      "type": "reference"
    },
    {
      "aggregatable": true,
      "custom": true,
      "defaultValue": null,
      "extraTypeInfo": null,
      "filterable": true,
      "groupable": true,
      "inlineHelpText": null,
      "label": "Approved On",
      "name": "vlocity_cmt__ApprovedOn__c",
      "nillable": true,
      "picklistValues": [],
      "referenceTo": [],
      "relationshipName": null,
      "sortable": true,
      "type": "date"
    },
    {
      "aggregatable": false,
      "custom": true,
      "defaultValue": null,
      "extraTypeInfo": "plaintextarea",
      "filterable": false,
      "groupable": false,
      "inlineHelpText": null,
      "label": "Attribute Default Values",
      "name": "vlocity_cmt__AttributeDefaultValues__c",
      "nillable": true,
      "picklistValues": [],
      "referenceTo": [],
      "relationshipName": null,
      "sortable": false,
      "type": "textarea"
    },
    {
      "aggregatable": false,
      "custom": true,
      "defaultValue": null,
      "extraTypeInfo": "plaintextarea",
      "filterable": false,
      "groupable": false,
      "inlineHelpText": null,
      "label": "Attribute Metadata",
      "name": "vlocity_cmt__AttributeMetadata__c",
      "nillable": true,
      "picklistValues": [],
      "referenceTo": [],
      "relationshipName": null,
      "sortable": false,
      "type": "textarea"
    },
    {
      "aggregatable": false,
      "custom": true,
      "defaultValue": null,
      "extraTypeInfo": "plaintextarea",
      "filterable": false,
      "groupable": false,
      "inlineHelpText": null,
      "label": "Attribute Rules",
      "name": "vlocity_cmt__AttributeRules__c",
      "nillable": true,
      "picklistValues": [],
      "referenceTo": [],
      "relationshipName": null,
      "sortable": false,
      "type": "textarea"
    },
    {
      "aggregatable": false,
      "custom": true,
      "defaultValue": null,
      "extraTypeInfo": "plaintextarea",
      "filterable": false,
      "groupable": false,
      "inlineHelpText": "Fulfillment Behavior",
      "label": "Fulfillment Behavior",
      "name": "vlocity_cmt__AttributesMarkupConfig__c",
      "nillable": true,
      "picklistValues": [],
      "referenceTo": [],
      "relationshipName": null,
      "sortable": false,
      "type": "textarea"
    },
    {
      "aggregatable": false,
      "custom": true,
      "defaultValue": null,
      "extraTypeInfo": "plaintextarea",
      "filterable": false,
      "groupable": false,
      "inlineHelpText": null,
      "label": "Category Data",
      "name": "vlocity_cmt__CategoryData__c",
      "nillable": true,
      "picklistValues": [],
      "referenceTo": [],
      "relationshipName": null,
      "sortable": false,
      "type": "textarea"
    },
    {
      "aggregatable": true,
      "custom": true,
      "defaultValue": null,
      "extraTypeInfo": null,
      "filterable": true,
      "groupable": true,
      "inlineHelpText": "Name of implementation which will be used by Change Detector in XOM",
      "label": "Change Detector Implementation",
      "name": "vlocity_cmt__ChangeDetectorImplementation__c",
      "nillable": true,
      "picklistValues": [],
      "referenceTo": [],
      "relationshipName": null,
      "sortable": true,
      "type": "string"
    },
    {
      "aggregatable": true,
      "custom": true,
      "defaultValue": null,
      "extraTypeInfo": null,
      "filterable": true,
      "groupable": true,
      "inlineHelpText": null,
      "label": "Class",
      "name": "vlocity_cmt__ClassId__c",
      "nillable": true,
      "picklistValues": [],
      "referenceTo": [
        "Product2"
      ],
      "relationshipName": "vlocity_cmt__ClassId__r",
      "sortable": true,
      "type": "reference"
    },
    {
      "aggregatable": true,
      "custom": true,
      "defaultValue": null,
      "extraTypeInfo": null,
      "filterable": true,
      "groupable": true,
      "inlineHelpText": null,
      "label": "Default Image",
      "name": "vlocity_cmt__DefaultImageId__c",
      "nillable": true,
      "picklistValues": [],
      "referenceTo": [
        "vlocity_cmt__VlocityAttachment__c"
      ],
      "relationshipName": "vlocity_cmt__DefaultImageId__r",
      "sortable": true,
      "type": "reference"
    },
    {
      "aggregatable": true,
      "custom": true,
      "defaultValue": null,
      "extraTypeInfo": null,
      "filterable": true,
      "groupable": true,
      "inlineHelpText": null,
      "label": "Effective Date",
      "name": "vlocity_cmt__EffectiveDate__c",
      "nillable": true,
      "picklistValues": [],
      "referenceTo": [],
      "relationshipName": null,
      "sortable": true,
      "type": "date"
    },
    {
      "aggregatable": true,
      "custom": true,
      "defaultValue": null,
      "extraTypeInfo": null,
      "filterable": true,
      "groupable": true,
      "inlineHelpText": null,
      "label": "End Date",
      "name": "vlocity_cmt__EndDate__c",
      "nillable": true,
      "picklistValues": [],
      "referenceTo": [],
      "relationshipName": null,
      "sortable": true,
      "type": "date"
    },
    {
      "aggregatable": true,
      "custom": true,
      "defaultValue": null,
      "extraTypeInfo": null,
      "filterable": true,
      "groupable": false,
      "inlineHelpText": null,
      "label": "End of Life Date",
      "name": "vlocity_cmt__EndOfLifeDate__c",
      "nillable": true,
      "picklistValues": [],
      "referenceTo": [],
      "relationshipName": null,
      "sortable": true,
      "type": "datetime"
    },
    {
      "aggregatable": true,
      "custom": true,
      "defaultValue": null,
      "extraTypeInfo": null,
      "filterable": true,
      "groupable": false,
      "inlineHelpText": null,
      "label": "Fulfilment Start Date",
      "name": "vlocity_cmt__FulfilmentStartDate__c",
      "nillable": true,
      "picklistValues": [],
      "referenceTo": [],
      "relationshipName": null,
      "sortable": true,
      "type": "datetime"
    },
    {
      "aggregatable": true,
      "custom": true,
      "defaultValue": null,
      "extraTypeInfo": null,
      "filterable": true,
      "groupable": true,
      "inlineHelpText": null,
      "label": "Version Group Key",
      "name": "vlocity_cmt__GlobalGroupKey__c",
      "nillable": true,
      "picklistValues": [],
      "referenceTo": [],
      "relationshipName": null,
      "sortable": true,
      "type": "string"
    },
    {
      "aggregatable": true,
      "custom": true,
      "defaultValue": null,
      "extraTypeInfo": null,
      "filterable": true,
      "groupable": true,
      "inlineHelpText": null,
      "label": "Global Key",
      "name": "vlocity_cmt__GlobalKey__c",
      "nillable": true,
      "picklistValues": [],
      "referenceTo": [],
      "relationshipName": null,
      "sortable": true,
      "type": "string"
    },
    {
      "aggregatable": false,
      "custom": true,
      "defaultValue": null,
      "extraTypeInfo": "plaintextarea",
      "filterable": false,
      "groupable": false,
      "inlineHelpText": "Stores the headers for Matrix is stored as a JSON.",
      "label": "Header Data",
      "name": "vlocity_cmt__HeaderData__c",
      "nillable": true,
      "picklistValues": [],
      "referenceTo": [],
      "relationshipName": null,
      "sortable": false,
      "type": "textarea"
    },
    {
      "aggregatable": false,
      "custom": true,
      "defaultValue": null,
      "extraTypeInfo": "plaintextarea",
      "filterable": false,
      "groupable": false,
      "inlineHelpText": null,
      "label": "Help Text",
      "name": "vlocity_cmt__HelpText__c",
      "nillable": true,
      "picklistValues": [],
      "referenceTo": [],
      "relationshipName": null,
      "sortable": false,
      "type": "textarea"
    },
    {
      "aggregatable": true,
      "custom": true,
      "defaultValue": null,
      "extraTypeInfo": null,
      "filterable": true,
      "groupable": true,
      "inlineHelpText": null,
      "label": "Image",
      "name": "vlocity_cmt__ImageId__c",
      "nillable": true,
      "picklistValues": [],
      "referenceTo": [],
      "relationshipName": null,
      "sortable": true,
      "type": "string"
    },
    {
      "aggregatable": false,
      "custom": true,
      "defaultValue": false,
      "extraTypeInfo": null,
      "filterable": true,
      "groupable": true,
      "inlineHelpText": null,
      "label": "Configurable",
      "name": "vlocity_cmt__IsConfigurable__c",
      "nillable": false,
      "picklistValues": [],
      "referenceTo": [],
      "relationshipName": null,
      "sortable": true,
      "type": "boolean"
    },
    {
      "aggregatable": false,
      "custom": true,
      "defaultValue": false,
      "extraTypeInfo": null,
      "filterable": true,
      "groupable": true,
      "inlineHelpText": null,
      "label": "Is Customer Subscription",
      "name": "vlocity_cmt__IsCustomerSubscription__c",
      "nillable": false,
      "picklistValues": [],
      "referenceTo": [],
      "relationshipName": null,
      "sortable": true,
      "type": "boolean"
    },
    {
      "aggregatable": false,
      "custom": true,
      "defaultValue": false,
      "extraTypeInfo": null,
      "filterable": true,
      "groupable": true,
      "inlineHelpText": null,
      "label": "Location Dependent",
      "name": "vlocity_cmt__IsLocationDependent__c",
      "nillable": false,
      "picklistValues": [],
      "referenceTo": [],
      "relationshipName": null,
      "sortable": true,
      "type": "boolean"
    },
    {
      "aggregatable": false,
      "custom": true,
      "defaultValue": false,
      "extraTypeInfo": null,
      "filterable": true,
      "groupable": true,
      "inlineHelpText": null,
      "label": "Not Assetizable",
      "name": "vlocity_cmt__IsNotAssetizable__c",
      "nillable": false,
      "picklistValues": [],
      "referenceTo": [],
      "relationshipName": null,
      "sortable": true,
      "type": "boolean"
    },
    {
      "aggregatable": false,
      "custom": true,
      "defaultValue": true,
      "extraTypeInfo": null,
      "filterable": true,
      "groupable": true,
      "inlineHelpText": null,
      "label": "Orderable",
      "name": "vlocity_cmt__IsOrderable__c",
      "nillable": false,
      "picklistValues": [],
      "referenceTo": [],
      "relationshipName": null,
      "sortable": true,
      "type": "boolean"
    },
    {
      "aggregatable": false,
      "custom": true,
      "defaultValue": null,
      "extraTypeInfo": "plaintextarea",
      "filterable": false,
      "groupable": false,
      "inlineHelpText": null,
      "label": "JSONAttribute",
      "name": "vlocity_cmt__JSONAttribute__c",
      "nillable": true,
      "picklistValues": [],
      "referenceTo": [],
      "relationshipName": null,
      "sortable": false,
      "type": "textarea"
    },
    {
      "aggregatable": true,
      "custom": true,
      "defaultValue": "Seconds",
      "extraTypeInfo": null,
      "filterable": true,
      "groupable": true,
      "inlineHelpText": null,
      "label": "Jeopardy Safety Interval Unit",
      "name": "vlocity_cmt__JeopardySafetyIntervalUnit__c",
      "nillable": true,
      "picklistValues": [
        {
          "active": true,
          "defaultValue": true,
          "label": "Seconds",
          "validFor": null,
          "value": "Seconds"
        },
        {
          "active": true,
          "defaultValue": false,
          "label": "Business Hours",
          "validFor": null,
          "value": "Business Hours"
        },
        {
          "active": true,
          "defaultValue": false,
          "label": "Business Days",
          "validFor": null,
          "value": "Business Days"
        },
        {
          "active": true,
          "defaultValue": false,
          "label": "Calendar Hours",
          "validFor": null,
          "value": "Calendar Hours"
        },
        {
          "active": true,
          "defaultValue": false,
          "label": "Calendar Days",
          "validFor": null,
          "value": "Calendar Days"
        }
      ],
      "referenceTo": [],
      "relationshipName": null,
      "sortable": true,
      "type": "picklist"
    },
    {
      "aggregatable": true,
      "custom": true,
      "defaultValue": null,
      "extraTypeInfo": null,
      "filterable": true,
      "groupable": false,
      "inlineHelpText": null,
      "label": "Jeopardy Safety Interval",
      "name": "vlocity_cmt__JeopardySafetyInterval__c",
      "nillable": true,
      "picklistValues": [],
      "referenceTo": [],
      "relationshipName": null,
      "sortable": true,
      "type": "double"
    },
    {
      "aggregatable": true,
      "custom": true,
      "defaultValue": "Draft",
      "extraTypeInfo": null,
      "filterable": true,
      "groupable": true,
      "inlineHelpText": null,
      "label": "Lifecycle Status",
      "name": "vlocity_cmt__LifecycleStatus__c",
      "nillable": true,
      "picklistValues": [
        {
          "active": true,
          "defaultValue": true,
          "label": "Draft",
          "validFor": null,
          "value": "Draft"
        },
        {
          "active": true,
          "defaultValue": false,
          "label": "Released",
          "validFor": null,
          "value": "Released"
        },
        {
          "active": true,
          "defaultValue": false,
          "label": "Amendment Pending",
          "validFor": null,
          "value": "Amendment Pending"
        }
      ],
      "referenceTo": [],
      "relationshipName": null,
      "sortable": true,
      "type": "picklist"
    },
    {
      "aggregatable": true,
      "custom": true,
      "defaultValue": null,
      "extraTypeInfo": null,
      "filterable": true,
      "groupable": true,
      "inlineHelpText": null,
      "label": "Main Feature Unit of Measure",
      "name": "vlocity_cmt__MainFeatureQuantityUom__c",
      "nillable": true,
      "picklistValues": [
        {
          "active": true,
          "defaultValue": false,
          "label": "GB",
          "validFor": null,
          "value": "GB"
        },
        {
          "active": true,
          "defaultValue": false,
          "label": "Currency",
          "validFor": null,
          "value": "Currency"
        },
        {
          "active": true,
          "defaultValue": false,
          "label": "Minute",
          "validFor": null,
          "value": "Minute"
        }
      ],
      "referenceTo": [],
      "relationshipName": null,
      "sortable": true,
      "type": "picklist"
    },
    {
      "aggregatable": true,
      "custom": true,
      "defaultValue": null,
      "extraTypeInfo": null,
      "filterable": true,
      "groupable": false,
      "inlineHelpText": null,
      "label": "Main Feature Quantity",
      "name": "vlocity_cmt__MainFeatureQuantity__c",
      "nillable": true,
      "picklistValues": [],
      "referenceTo": [],
      "relationshipName": null,
      "sortable": true,
      "type": "double"
    },
    {
      "aggregatable": true,
      "custom": true,
      "defaultValue": null,
      "extraTypeInfo": null,
      "filterable": true,
      "groupable": false,
      "inlineHelpText": null,
      "label": "Main Feature Term in Days",
      "name": "vlocity_cmt__MainFeatureTermInDays__c",
      "nillable": true,
      "picklistValues": [],
      "referenceTo": [],
      "relationshipName": null,
      "sortable": true,
      "type": "double"
    },
    {
      "aggregatable": true,
      "custom": true,
      "defaultValue": null,
      "extraTypeInfo": null,
      "filterable": true,
      "groupable": false,
      "inlineHelpText": null,
      "label": "Modification#",
      "name": "vlocity_cmt__Modification__c",
      "nillable": true,
      "picklistValues": [],
      "referenceTo": [],
      "relationshipName": null,
      "sortable": true,
      "type": "double"
    },
    {
      "aggregatable": true,
      "custom": true,
      "defaultValue": null,
      "extraTypeInfo": null,
      "filterable": true,
      "groupable": true,
      "inlineHelpText": null,
      "label": "Object Type",
      "name": "vlocity_cmt__ObjectTypeId__c",
      "nillable": true,
      "picklistValues": [],
      "referenceTo": [
        "vlocity_cmt__ObjectClass__c"
      ],
      "relationshipName": "vlocity_cmt__ObjectTypeId__r",
      "sortable": true,
      "type": "reference"
    },
    {
      "aggregatable": true,
      "custom": true,
      "defaultValue": null,
      "extraTypeInfo": null,
      "filterable": true,
      "groupable": true,
      "inlineHelpText": null,
      "label": "Parent Class",
      "name": "vlocity_cmt__ParentClassId__c",
      "nillable": true,
      "picklistValues": [],
      "referenceTo": [
        "Product2"
      ],
      "relationshipName": "vlocity_cmt__ParentClassId__r",
      "sortable": true,
      "type": "reference"
    },
    {
      "aggregatable": true,
      "custom": true,
      "defaultValue": null,
      "extraTypeInfo": null,
      "filterable": true,
      "groupable": true,
      "inlineHelpText": null,
      "label": "Product Spec",
      "name": "vlocity_cmt__ProductSpecId__c",
      "nillable": true,
      "picklistValues": [],
      "referenceTo": [
        "Product2"
      ],
      "relationshipName": "vlocity_cmt__ProductSpecId__r",
      "sortable": true,
      "type": "reference"
    },
    {
      "aggregatable": true,
      "custom": true,
      "defaultValue": null,
      "extraTypeInfo": null,
      "filterable": true,
      "groupable": true,
      "inlineHelpText": null,
      "label": "Product Template",
      "name": "vlocity_cmt__ProductTemplateProductId__c",
      "nillable": true,
      "picklistValues": [],
      "referenceTo": [
        "Product2"
      ],
      "relationshipName": "vlocity_cmt__ProductTemplateProductId__r",
      "sortable": true,
      "type": "reference"
    },
    {
      "aggregatable": true,
      "custom": true,
      "defaultValue": "Order Item",
      "extraTypeInfo": null,
      "filterable": true,
      "groupable": true,
      "inlineHelpText": null,
      "label": "Scope",
      "name": "vlocity_cmt__Scope__c",
      "nillable": true,
      "picklistValues": [
        {
          "active": true,
          "defaultValue": false,
          "label": "Account",
          "validFor": null,
          "value": "Account"
        },
        {
          "active": true,
          "defaultValue": true,
          "label": "Order Item",
          "validFor": null,
          "value": "Order Item"
        },
        {
          "active": true,
          "defaultValue": false,
          "label": "Downstream Order Item",
          "validFor": null,
          "value": "Downstream Order Item"
        },
        {
          "active": true,
          "defaultValue": false,
          "label": "Top Order Item",
          "validFor": null,
          "value": "Top Order Item"
        },
        {
          "active": true,
          "defaultValue": false,
          "label": "Incremental",
          "validFor": null,
          "value": "Incremental"
        },
        {
          "active": true,
          "defaultValue": false,
          "label": "Order",
          "validFor": null,
          "value": "Order"
        },
        {
          "active": true,
          "defaultValue": false,
          "label": "Relies On",
          "validFor": null,
          "value": "Relies On"
        }
      ],
      "referenceTo": [],
      "relationshipName": null,
      "sortable": true,
      "type": "picklist"
    },
    {
      "aggregatable": true,
      "custom": true,
      "defaultValue": null,
      "extraTypeInfo": null,
      "filterable": true,
      "groupable": false,
      "inlineHelpText": null,
      "label": "Selling End Date",
      "name": "vlocity_cmt__SellingEndDate__c",
      "nillable": true,
      "picklistValues": [],
      "referenceTo": [],
      "relationshipName": null,
      "sortable": true,
      "type": "datetime"
    },
    {
      "aggregatable": true,
      "custom": true,
      "defaultValue": null,
      "extraTypeInfo": null,
      "filterable": true,
      "groupable": false,
      "inlineHelpText": null,
      "label": "Selling Start Date",
      "name": "vlocity_cmt__SellingStartDate__c",
      "nillable": true,
      "picklistValues": [],
      "referenceTo": [],
      "relationshipName": null,
      "sortable": true,
      "type": "datetime"
    },
    {
      "aggregatable": true,
      "custom": true,
      "defaultValue": null,
      "extraTypeInfo": null,
      "filterable": true,
      "groupable": true,
      "inlineHelpText": null,
      "label": "Specification Sub Type",
      "name": "vlocity_cmt__SpecificationSubType__c",
      "nillable": true,
      "picklistValues": [
        {
          "active": true,
          "defaultValue": false,
          "label": "Simple",
          "validFor": null,
          "value": "Simple"
        },
        {
          "active": true,
          "defaultValue": false,
          "label": "Bundle",
          "validFor": null,
          "value": "Bundle"
        }
      ],
      "referenceTo": [],
      "relationshipName": null,
      "sortable": true,
      "type": "picklist"
    },
    {
      "aggregatable": true,
      "custom": true,
      "defaultValue": null,
      "extraTypeInfo": null,
      "filterable": true,
      "groupable": true,
      "inlineHelpText": null,
      "label": "Specification Type",
      "name": "vlocity_cmt__SpecificationType__c",
      "nillable": true,
      "picklistValues": [
        {
          "active": true,
          "defaultValue": false,
          "label": "Resource",
          "validFor": null,
          "value": "Resource"
        },
        {
          "active": true,
          "defaultValue": false,
          "label": "Service",
          "validFor": null,
          "value": "Service"
        },
        {
          "active": true,
          "defaultValue": false,
          "label": "Product",
          "validFor": null,
          "value": "Product"
        },
        {
          "active": true,
          "defaultValue": false,
          "label": "Offer",
          "validFor": null,
          "value": "Offer"
        }
      ],
      "referenceTo": [],
      "relationshipName": null,
      "sortable": true,
      "type": "picklist"
    },
    {
      "aggregatable": true,
      "custom": true,
      "defaultValue": null,
      "extraTypeInfo": null,
      "filterable": true,
      "groupable": false,
      "inlineHelpText": null,
      "label": "Standard Premium",
      "name": "vlocity_cmt__StandardPremium__c",
      "nillable": true,
      "picklistValues": [],
      "referenceTo": [],
      "relationshipName": null,
      "sortable": true,
      "type": "currency"
    },
    {
      "aggregatable": true,
      "custom": true,
      "defaultValue": null,
      "extraTypeInfo": null,
      "filterable": true,
      "groupable": true,
      "inlineHelpText": null,
      "label": "Status",
      "name": "vlocity_cmt__Status__c",
      "nillable": true,
      "picklistValues": [
        {
          "active": true,
          "defaultValue": false,
          "label": "Draft",
          "validFor": null,
          "value": "Draft"
        },
        {
          "active": true,
          "defaultValue": false,
          "label": "Pending Approval",
          "validFor": null,
          "value": "Pending Approval"
        },
        {
          "active": true,
          "defaultValue": false,
          "label": "Active",
          "validFor": null,
          "value": "Active"
        }
      ],
      "referenceTo": [],
      "relationshipName": null,
      "sortable": true,
      "type": "picklist"
    },
    {
      "aggregatable": true,
      "custom": true,
      "defaultValue": null,
      "extraTypeInfo": null,
      "filterable": true,
      "groupable": false,
      "inlineHelpText": null,
      "label": "Time To Live",
      "name": "vlocity_cmt__TimeToLive__c",
      "nillable": true,
      "picklistValues": [],
      "referenceTo": [],
      "relationshipName": null,
      "sortable": true,
      "type": "double"
    },
    {
      "aggregatable": false,
      "custom": true,
      "defaultValue": false,
      "extraTypeInfo": null,
      "filterable": true,
      "groupable": true,
      "inlineHelpText": null,
      "label": "Track As Agreement",
      "name": "vlocity_cmt__TrackAsAgreement__c",
      "nillable": false,
      "picklistValues": [],
      "referenceTo": [],
      "relationshipName": null,
      "sortable": true,
      "type": "boolean"
    },
    {
      "aggregatable": true,
      "custom": true,
      "defaultValue": "None",
      "extraTypeInfo": null,
      "filterable": true,
      "groupable": true,
      "inlineHelpText": null,
      "label": "Type",
      "name": "vlocity_cmt__Type__c",
      "nillable": true,
      "picklistValues": [
        {
          "active": true,
          "defaultValue": true,
          "label": "None",
          "validFor": null,
          "value": "None"
        },
        {
          "active": true,
          "defaultValue": false,
          "label": "Plan",
          "validFor": null,
          "value": "Plan"
        },
        {
          "active": true,
          "defaultValue": false,
          "label": "Service",
          "validFor": null,
          "value": "Service"
        },
        {
          "active": true,
          "defaultValue": false,
          "label": "SIM Card",
          "validFor": null,
          "value": "SIM Card"
        },
        {
          "active": true,
          "defaultValue": false,
          "label": "Add On",
          "validFor": null,
          "value": "Add On"
        },
        {
          "active": true,
          "defaultValue": false,
          "label": "Fee",
          "validFor": null,
          "value": "Fee"
        },
        {
          "active": true,
          "defaultValue": false,
          "label": "Top Up",
          "validFor": null,
          "value": "Top Up"
        },
        {
          "active": true,
          "defaultValue": false,
          "label": "Handset",
          "validFor": null,
          "value": "Handset"
        }
      ],
      "referenceTo": [],
      "relationshipName": null,
      "sortable": true,
      "type": "picklist"
    },
    {
      "aggregatable": true,
      "custom": true,
      "defaultValue": null,
      "extraTypeInfo": null,
      "filterable": true,
      "groupable": true,
      "inlineHelpText": null,
      "label": "Vendor",
      "name": "vlocity_cmt__VendorAccountId__c",
      "nillable": true,
      "picklistValues": [],
      "referenceTo": [
        "Account"
      ],
      "relationshipName": "vlocity_cmt__VendorAccountId__r",
      "sortable": true,
      "type": "reference"
    },
    {
      "aggregatable": true,
      "custom": true,
      "defaultValue": null,
      "extraTypeInfo": null,
      "filterable": true,
      "groupable": false,
      "inlineHelpText": null,
      "label": "Version End Date",
      "name": "vlocity_cmt__VersionEndDateTime__c",
      "nillable": true,
      "picklistValues": [],
      "referenceTo": [],
      "relationshipName": null,
      "sortable": true,
      "type": "datetime"
    },
    {
      "aggregatable": true,
      "custom": true,
      "defaultValue": null,
      "extraTypeInfo": null,
      "filterable": true,
      "groupable": true,
      "inlineHelpText": null,
      "label": "Version Label",
      "name": "vlocity_cmt__VersionLabel__c",
      "nillable": true,
      "picklistValues": [],
      "referenceTo": [],
      "relationshipName": null,
      "sortable": true,
      "type": "string"
    },
    {
      "aggregatable": true,
      "custom": true,
      "defaultValue": null,
      "extraTypeInfo": null,
      "filterable": true,
      "groupable": false,
      "inlineHelpText": null,
      "label": "Version Start Date",
      "name": "vlocity_cmt__VersionStartDateTime__c",
      "nillable": true,
      "picklistValues": [],
      "referenceTo": [],
      "relationshipName": null,
      "sortable": true,
      "type": "datetime"
    },
    {
      "aggregatable": true,
      "custom": true,
      "defaultValue": null,
      "extraTypeInfo": null,
      "filterable": true,
      "groupable": false,
      "inlineHelpText": null,
      "label": "Object Type Name",
      "name": "vlocity_cmt__ObjectTypeName__c",
      "nillable": true,
      "picklistValues": [],
      "referenceTo": [],
      "relationshipName": null,
      "sortable": true,
      "type": "string"
    },
    {
      "aggregatable": true,
      "custom": true,
      "defaultValue": null,
      "extraTypeInfo": null,
      "filterable": true,
      "groupable": false,
      "inlineHelpText": null,
      "label": "Parent Class Code",
      "name": "vlocity_cmt__ParentClassCode__c",
      "nillable": true,
      "picklistValues": [],
      "referenceTo": [],
      "relationshipName": null,
      "sortable": true,
      "type": "string"
    },
    {
      "aggregatable": true,
      "custom": true,
      "defaultValue": null,
      "extraTypeInfo": null,
      "filterable": true,
      "groupable": false,
      "inlineHelpText": null,
      "label": "Specification Type Name",
      "name": "vlocity_cmt__ProductSpecName__c",
      "nillable": true,
      "picklistValues": [],
      "referenceTo": [],
      "relationshipName": null,
      "sortable": true,
      "type": "string"
    },
    {
      "aggregatable": true,
      "custom": true,
      "defaultValue": "None",
      "extraTypeInfo": null,
      "filterable": true,
      "groupable": true,
      "inlineHelpText": null,
      "label": "Sub Type",
      "name": "vlocity_cmt__SubType__c",
      "nillable": true,
      "picklistValues": [
        {
          "active": true,
          "defaultValue": true,
          "label": "None",
          "validFor": "gAAA",
          "value": "None"
        },
        {
          "active": true,
          "defaultValue": false,
          "label": "Postpaid",
          "validFor": "QAAA",
          "value": "Postpaid"
        },
        {
          "active": true,
          "defaultValue": false,
          "label": "Prepaid",
          "validFor": "QAAA",
          "value": "Prepaid"
        }
      ],
      "referenceTo": [],
      "relationshipName": null,
      "sortable": true,
      "type": "picklist"
    }
  ],
  "label": "Product",
  "childRelationships": [
    {
      "cascadeDelete": true,
      "childSObject": "AIInsightValue",
      "deprecatedAndHidden": false,
      "field": "SobjectLookupValueId",
      "junctionIdListNames": [],
      "junctionReferenceTo": [],
      "relationshipName": null,
      "restrictedDelete": false
    },
    {
      "cascadeDelete": false,
      "childSObject": "AIRecordInsight",
      "deprecatedAndHidden": false,
      "field": "TargetId",
      "junctionIdListNames": [],
      "junctionReferenceTo": [],
      "relationshipName": null,
      "restrictedDelete": false
    },
    {
      "cascadeDelete": true,
      "childSObject": "ActivityHistory",
      "deprecatedAndHidden": false,
      "field": "WhatId",
      "junctionIdListNames": [],
      "junctionReferenceTo": [],
      "relationshipName": "ActivityHistories",
      "restrictedDelete": false
    },
    {
      "cascadeDelete": false,
      "childSObject": "Asset",
      "deprecatedAndHidden": false,
      "field": "Product2Id",
      "junctionIdListNames": [],
      "junctionReferenceTo": [],
      "relationshipName": "Assets",
      "restrictedDelete": true
    },
    {
      "cascadeDelete": false,
      "childSObject": "AssetChangeEvent",
      "deprecatedAndHidden": false,
      "field": "Product2Id",
      "junctionIdListNames": [],
      "junctionReferenceTo": [],
      "relationshipName": null,
      "restrictedDelete": false
    },
    {
      "cascadeDelete": true,
      "childSObject": "AttachedContentDocument",
      "deprecatedAndHidden": false,
      "field": "LinkedEntityId",
      "junctionIdListNames": [],
      "junctionReferenceTo": [],
      "relationshipName": "AttachedContentDocuments",
      "restrictedDelete": false
    },
    {
      "cascadeDelete": true,
      "childSObject": "AttachedContentNote",
      "deprecatedAndHidden": false,
      "field": "LinkedEntityId",
      "junctionIdListNames": [],
      "junctionReferenceTo": [],
      "relationshipName": "AttachedContentNotes",
      "restrictedDelete": false
    },
    {
      "cascadeDelete": true,
      "childSObject": "Attachment",
      "deprecatedAndHidden": false,
      "field": "ParentId",
      "junctionIdListNames": [],
      "junctionReferenceTo": [],
      "relationshipName": "Attachments",
      "restrictedDelete": false
    },
    {
      "cascadeDelete": false,
      "childSObject": "BusinessAlert",
      "deprecatedAndHidden": false,
      "field": "AlertRecordId",
      "junctionIdListNames": [],
      "junctionReferenceTo": [],
      "relationshipName": null,
      "restrictedDelete": true
    },
    {
      "cascadeDelete": true,
      "childSObject": "CombinedAttachment",
      "deprecatedAndHidden": false,
      "field": "ParentId",
      "junctionIdListNames": [],
      "junctionReferenceTo": [],
      "relationshipName": "CombinedAttachments",
      "restrictedDelete": false
    },
    {
      "cascadeDelete": true,
      "childSObject": "ContentDocumentLink",
      "deprecatedAndHidden": false,
      "field": "LinkedEntityId",
      "junctionIdListNames": [],
      "junctionReferenceTo": [],
      "relationshipName": "ContentDocumentLinks",
      "restrictedDelete": false
    },
    {
      "cascadeDelete": false,
      "childSObject": "ContentDocumentLinkChangeEvent",
      "deprecatedAndHidden": false,
      "field": "LinkedEntityId",
      "junctionIdListNames": [],
      "junctionReferenceTo": [],
      "relationshipName": null,
      "restrictedDelete": false
    },
    {
      "cascadeDelete": false,
      "childSObject": "ContentVersion",
      "deprecatedAndHidden": false,
      "field": "FirstPublishLocationId",
      "junctionIdListNames": [],
      "junctionReferenceTo": [],
      "relationshipName": null,
      "restrictedDelete": false
    },
    {
      "cascadeDelete": false,
      "childSObject": "ContentVersionChangeEvent",
      "deprecatedAndHidden": false,
      "field": "FirstPublishLocationId",
      "junctionIdListNames": [],
      "junctionReferenceTo": [],
      "relationshipName": null,
      "restrictedDelete": false
    },
    {
      "cascadeDelete": false,
      "childSObject": "ContractLineItem",
      "deprecatedAndHidden": false,
      "field": "Product2Id",
      "junctionIdListNames": [],
      "junctionReferenceTo": [],
      "relationshipName": "ContractLineItems",
      "restrictedDelete": false
    },
    {
      "cascadeDelete": false,
      "childSObject": "EmailMessage",
      "deprecatedAndHidden": false,
      "field": "RelatedToId",
      "junctionIdListNames": [],
      "junctionReferenceTo": [],
      "relationshipName": "Emails",
      "restrictedDelete": false
    },
    {
      "cascadeDelete": false,
      "childSObject": "EmailMessageChangeEvent",
      "deprecatedAndHidden": false,
      "field": "RelatedToId",
      "junctionIdListNames": [],
      "junctionReferenceTo": [],
      "relationshipName": null,
      "restrictedDelete": false
    },
    {
      "cascadeDelete": false,
      "childSObject": "EngagementTopic",
      "deprecatedAndHidden": false,
      "field": "TopicId",
      "junctionIdListNames": [],
      "junctionReferenceTo": [],
      "relationshipName": "EngagementInitiatedTopic",
      "restrictedDelete": false
    },
    {
      "cascadeDelete": true,
      "childSObject": "EntitySubscription",
      "deprecatedAndHidden": false,
      "field": "ParentId",
      "junctionIdListNames": [],
      "junctionReferenceTo": [],
      "relationshipName": "FeedSubscriptionsForEntity",
      "restrictedDelete": false
    },
    {
      "cascadeDelete": true,
      "childSObject": "Event",
      "deprecatedAndHidden": false,
      "field": "WhatId",
      "junctionIdListNames": [],
      "junctionReferenceTo": [],
      "relationshipName": "Events",
      "restrictedDelete": false
    },
    {
      "cascadeDelete": false,
      "childSObject": "EventChangeEvent",
      "deprecatedAndHidden": false,
      "field": "WhatId",
      "junctionIdListNames": [],
      "junctionReferenceTo": [],
      "relationshipName": null,
      "restrictedDelete": false
    },
    {
      "cascadeDelete": true,
      "childSObject": "EventRelation",
      "deprecatedAndHidden": false,
      "field": "RelationId",
      "junctionIdListNames": [],
      "junctionReferenceTo": [],
      "relationshipName": "EventRelations",
      "restrictedDelete": false
    },
    {
      "cascadeDelete": false,
      "childSObject": "EventRelationChangeEvent",
      "deprecatedAndHidden": false,
      "field": "RelationId",
      "junctionIdListNames": [],
      "junctionReferenceTo": [],
      "relationshipName": null,
      "restrictedDelete": false
    },
    {
      "cascadeDelete": false,
      "childSObject": "FeedComment",
      "deprecatedAndHidden": false,
      "field": "ParentId",
      "junctionIdListNames": [],
      "junctionReferenceTo": [],
      "relationshipName": null,
      "restrictedDelete": false
    },
    {
      "cascadeDelete": true,
      "childSObject": "FeedItem",
      "deprecatedAndHidden": false,
      "field": "ParentId",
      "junctionIdListNames": [],
      "junctionReferenceTo": [],
      "relationshipName": null,
      "restrictedDelete": false
    },
    {
      "cascadeDelete": false,
      "childSObject": "FlowExecutionErrorEvent",
      "deprecatedAndHidden": false,
      "field": "ContextRecordId",
      "junctionIdListNames": [],
      "junctionReferenceTo": [],
      "relationshipName": null,
      "restrictedDelete": false
    },
    {
      "cascadeDelete": false,
      "childSObject": "FlowOrchestrationWorkItem",
      "deprecatedAndHidden": false,
      "field": "RelatedRecordId",
      "junctionIdListNames": [],
      "junctionReferenceTo": [],
      "relationshipName": "FlowOrchestrationWorkItems",
      "restrictedDelete": false
    },
    {
      "cascadeDelete": false,
      "childSObject": "FlowRecordRelation",
      "deprecatedAndHidden": false,
      "field": "RelatedRecordId",
      "junctionIdListNames": [],
      "junctionReferenceTo": [],
      "relationshipName": null,
      "restrictedDelete": false
    },
    {
      "cascadeDelete": true,
      "childSObject": "Note",
      "deprecatedAndHidden": false,
      "field": "ParentId",
      "junctionIdListNames": [],
      "junctionReferenceTo": [],
      "relationshipName": "Notes",
      "restrictedDelete": false
    },
    {
      "cascadeDelete": true,
      "childSObject": "NoteAndAttachment",
      "deprecatedAndHidden": false,
      "field": "ParentId",
      "junctionIdListNames": [],
      "junctionReferenceTo": [],
      "relationshipName": "NotesAndAttachments",
      "restrictedDelete": false
    },
    {
      "cascadeDelete": true,
      "childSObject": "OpenActivity",
      "deprecatedAndHidden": false,
      "field": "WhatId",
      "junctionIdListNames": [],
      "junctionReferenceTo": [],
      "relationshipName": "OpenActivities",
      "restrictedDelete": false
    },
    {
      "cascadeDelete": false,
      "childSObject": "OpportunityLineItem",
      "deprecatedAndHidden": false,
      "field": "Product2Id",
      "junctionIdListNames": [],
      "junctionReferenceTo": [],
      "relationshipName": null,
      "restrictedDelete": false
    },
    {
      "cascadeDelete": false,
      "childSObject": "OpportunityLineItem",
      "deprecatedAndHidden": false,
      "field": "vlocity_cmt__Product2Id__c",
      "junctionIdListNames": [],
      "junctionReferenceTo": [],
      "relationshipName": "vlocity_cmt__Opportunity_Product__r",
      "restrictedDelete": false
    },
    {
      "cascadeDelete": false,
      "childSObject": "OrderItem",
      "deprecatedAndHidden": false,
      "field": "Product2Id",
      "junctionIdListNames": [],
      "junctionReferenceTo": [],
      "relationshipName": null,
      "restrictedDelete": true
    },
    {
      "cascadeDelete": false,
      "childSObject": "OrderItem",
      "deprecatedAndHidden": false,
      "field": "vlocity_cmt__Product2Id__c",
      "junctionIdListNames": [],
      "junctionReferenceTo": [],
      "relationshipName": "vlocity_cmt__OrderProducts__r",
      "restrictedDelete": false
    },
    {
      "cascadeDelete": false,
      "childSObject": "OrderItemChangeEvent",
      "deprecatedAndHidden": false,
      "field": "Product2Id",
      "junctionIdListNames": [],
      "junctionReferenceTo": [],
      "relationshipName": null,
      "restrictedDelete": false
    },
    {
      "cascadeDelete": false,
      "childSObject": "OutgoingEmail",
      "deprecatedAndHidden": false,
      "field": "RelatedToId",
      "junctionIdListNames": [],
      "junctionReferenceTo": [],
      "relationshipName": null,
      "restrictedDelete": false
    },
    {
      "cascadeDelete": true,
      "childSObject": "PricebookEntry",
      "deprecatedAndHidden": false,
      "field": "Product2Id",
      "junctionIdListNames": [],
      "junctionReferenceTo": [],
      "relationshipName": "PricebookEntries",
      "restrictedDelete": true
    },
    {
      "cascadeDelete": false,
      "childSObject": "PricebookEntryChangeEvent",
      "deprecatedAndHidden": false,
      "field": "Product2Id",
      "junctionIdListNames": [],
      "junctionReferenceTo": [],
      "relationshipName": null,
      "restrictedDelete": false
    },
    {
      "cascadeDelete": true,
      "childSObject": "ProcessInstance",
      "deprecatedAndHidden": false,
      "field": "TargetObjectId",
      "junctionIdListNames": [],
      "junctionReferenceTo": [],
      "relationshipName": "ProcessInstances",
      "restrictedDelete": false
    },
    {
      "cascadeDelete": false,
      "childSObject": "ProcessInstanceHistory",
      "deprecatedAndHidden": false,
      "field": "TargetObjectId",
      "junctionIdListNames": [],
      "junctionReferenceTo": [],
      "relationshipName": "ProcessSteps",
      "restrictedDelete": false
    },
    {
      "cascadeDelete": false,
      "childSObject": "Product2",
      "deprecatedAndHidden": false,
      "field": "vlocity_cmt__ClassId__c",
      "junctionIdListNames": [],
      "junctionReferenceTo": [],
      "relationshipName": "vlocity_cmt__ClassProducts__r",
      "restrictedDelete": false
    },
    {
      "cascadeDelete": false,
      "childSObject": "Product2",
      "deprecatedAndHidden": false,
      "field": "vlocity_cmt__ParentClassId__c",
      "junctionIdListNames": [],
      "junctionReferenceTo": [],
      "relationshipName": "vlocity_cmt__Subclasses__r",
      "restrictedDelete": false
    },
    {
      "cascadeDelete": false,
      "childSObject": "Product2",
      "deprecatedAndHidden": false,
      "field": "vlocity_cmt__ProductSpecId__c",
      "junctionIdListNames": [],
      "junctionReferenceTo": [],
      "relationshipName": "vlocity_cmt__ProductSpecOffers__r",
      "restrictedDelete": false
    },
    {
      "cascadeDelete": false,
      "childSObject": "Product2",
      "deprecatedAndHidden": false,
      "field": "vlocity_cmt__ProductTemplateProductId__c",
      "junctionIdListNames": [],
      "junctionReferenceTo": [],
      "relationshipName": "vlocity_cmt__ProductTemplateProducts__r",
      "restrictedDelete": false
    },
    {
      "cascadeDelete": true,
      "childSObject": "Product2Feed",
      "deprecatedAndHidden": false,
      "field": "ParentId",
      "junctionIdListNames": [],
      "junctionReferenceTo": [],
      "relationshipName": "Feeds",
      "restrictedDelete": false
    },
    {
      "cascadeDelete": true,
      "childSObject": "Product2History",
      "deprecatedAndHidden": false,
      "field": "Product2Id",
      "junctionIdListNames": [],
      "junctionReferenceTo": [],
      "relationshipName": "Histories",
      "restrictedDelete": false
    },
    {
      "cascadeDelete": false,
      "childSObject": "ProductConsumed",
      "deprecatedAndHidden": false,
      "field": "Product2Id",
      "junctionIdListNames": [],
      "junctionReferenceTo": [],
      "relationshipName": "ProductsConsumed",
      "restrictedDelete": false
    },
    {
      "cascadeDelete": false,
      "childSObject": "ProductEntitlementTemplate",
      "deprecatedAndHidden": false,
      "field": "Product2Id",
      "junctionIdListNames": [],
      "junctionReferenceTo": [],
      "relationshipName": null,
      "restrictedDelete": false
    },
    {
      "cascadeDelete": true,
      "childSObject": "ProductItem",
      "deprecatedAndHidden": false,
      "field": "Product2Id",
      "junctionIdListNames": [],
      "junctionReferenceTo": [],
      "relationshipName": "ProductItems",
      "restrictedDelete": false
    },
    {
      "cascadeDelete": false,
      "childSObject": "ProductItemChangeEvent",
      "deprecatedAndHidden": false,
      "field": "Product2Id",
      "junctionIdListNames": [],
      "junctionReferenceTo": [],
      "relationshipName": null,
      "restrictedDelete": false
    },
    {
      "cascadeDelete": true,
      "childSObject": "ProductRequestLineItem",
      "deprecatedAndHidden": false,
      "field": "Product2Id",
      "junctionIdListNames": [],
      "junctionReferenceTo": [],
      "relationshipName": "ProductRequestLineItems",
      "restrictedDelete": false
    },
    {
      "cascadeDelete": false,
      "childSObject": "ProductRequestLineItemChangeEvent",
      "deprecatedAndHidden": false,
      "field": "Product2Id",
      "junctionIdListNames": [],
      "junctionReferenceTo": [],
      "relationshipName": null,
      "restrictedDelete": false
    },
    {
      "cascadeDelete": true,
      "childSObject": "ProductRequired",
      "deprecatedAndHidden": false,
      "field": "Product2Id",
      "junctionIdListNames": [],
      "junctionReferenceTo": [],
      "relationshipName": "ProductsRequired",
      "restrictedDelete": false
    },
    {
      "cascadeDelete": false,
      "childSObject": "ProductRequiredChangeEvent",
      "deprecatedAndHidden": false,
      "field": "Product2Id",
      "junctionIdListNames": [],
      "junctionReferenceTo": [],
      "relationshipName": null,
      "restrictedDelete": false
    },
    {
      "cascadeDelete": false,
      "childSObject": "ProductServiceCampaign",
      "deprecatedAndHidden": false,
      "field": "Product2Id",
      "junctionIdListNames": [],
      "junctionReferenceTo": [],
      "relationshipName": "ProductServiceCampaignProducts",
      "restrictedDelete": false
    },
    {
      "cascadeDelete": false,
      "childSObject": "ProductServiceCampaignItem",
      "deprecatedAndHidden": false,
      "field": "Product2Id",
      "junctionIdListNames": [],
      "junctionReferenceTo": [],
      "relationshipName": "ProductServiceCampaignItems",
      "restrictedDelete": true
    },
    {
      "cascadeDelete": true,
      "childSObject": "ProductTransfer",
      "deprecatedAndHidden": false,
      "field": "Product2Id",
      "junctionIdListNames": [],
      "junctionReferenceTo": [],
      "relationshipName": "ProductTransfers",
      "restrictedDelete": false
    },
    {
      "cascadeDelete": false,
      "childSObject": "ProductTransferChangeEvent",
      "deprecatedAndHidden": false,
      "field": "Product2Id",
      "junctionIdListNames": [],
      "junctionReferenceTo": [],
      "relationshipName": null,
      "restrictedDelete": false
    },
    {
      "cascadeDelete": false,
      "childSObject": "ProductWarrantyTerm",
      "deprecatedAndHidden": false,
      "field": "CoveredProductId",
      "junctionIdListNames": [],
      "junctionReferenceTo": [],
      "relationshipName": "ProductWarrantyTermProducts",
      "restrictedDelete": false
    },
    {
      "cascadeDelete": false,
      "childSObject": "QuoteLineItem",
      "deprecatedAndHidden": false,
      "field": "Product2Id",
      "junctionIdListNames": [],
      "junctionReferenceTo": [],
      "relationshipName": null,
      "restrictedDelete": true
    },
    {
      "cascadeDelete": false,
      "childSObject": "QuoteLineItem",
      "deprecatedAndHidden": false,
      "field": "vlocity_cmt__Product2Id__c",
      "junctionIdListNames": [],
      "junctionReferenceTo": [],
      "relationshipName": "vlocity_cmt__Quote_Line_Items__r",
      "restrictedDelete": false
    },
    {
      "cascadeDelete": false,
      "childSObject": "QuoteLineItemChangeEvent",
      "deprecatedAndHidden": false,
      "field": "Product2Id",
      "junctionIdListNames": [],
      "junctionReferenceTo": [],
      "relationshipName": null,
      "restrictedDelete": false
    },
    {
      "cascadeDelete": true,
      "childSObject": "RecordAction",
      "deprecatedAndHidden": false,
      "field": "RecordId",
      "junctionIdListNames": [],
      "junctionReferenceTo": [],
      "relationshipName": "RecordActions",
      "restrictedDelete": false
    },
    {
      "cascadeDelete": false,
      "childSObject": "RecordActionHistory",
      "deprecatedAndHidden": false,
      "field": "ParentRecordId",
      "junctionIdListNames": [],
      "junctionReferenceTo": [],
      "relationshipName": "RecordActionHistories",
      "restrictedDelete": false
    },
    {
      "cascadeDelete": true,
      "childSObject": "ReturnOrderLineItem",
      "deprecatedAndHidden": false,
      "field": "Product2Id",
      "junctionIdListNames": [],
      "junctionReferenceTo": [],
      "relationshipName": "ReturnOrderLineItems",
      "restrictedDelete": false
    },
    {
      "cascadeDelete": false,
      "childSObject": "ReturnOrderLineItemChangeEvent",
      "deprecatedAndHidden": false,
      "field": "Product2Id",
      "junctionIdListNames": [],
      "junctionReferenceTo": [],
      "relationshipName": null,
      "restrictedDelete": false
    },
    {
      "cascadeDelete": true,
      "childSObject": "SerializedProduct",
      "deprecatedAndHidden": false,
      "field": "Product2Id",
      "junctionIdListNames": [],
      "junctionReferenceTo": [],
      "relationshipName": "SerializedProducts",
      "restrictedDelete": false
    },
    {
      "cascadeDelete": false,
      "childSObject": "ShipmentItem",
      "deprecatedAndHidden": false,
      "field": "Product2Id",
      "junctionIdListNames": [],
      "junctionReferenceTo": [],
      "relationshipName": "ShipmentItems",
      "restrictedDelete": false
    },
    {
      "cascadeDelete": false,
      "childSObject": "SvcCatalogReqExtdAttrVal",
      "deprecatedAndHidden": false,
      "field": "ReferenceRecordId",
      "junctionIdListNames": [],
      "junctionReferenceTo": [],
      "relationshipName": null,
      "restrictedDelete": false
    },
    {
      "cascadeDelete": false,
      "childSObject": "SvcCatalogReqRelatedItem",
      "deprecatedAndHidden": false,
      "field": "RelatedInternalRecordId",
      "junctionIdListNames": [],
      "junctionReferenceTo": [],
      "relationshipName": null,
      "restrictedDelete": false
    },
    {
      "cascadeDelete": true,
      "childSObject": "Task",
      "deprecatedAndHidden": false,
      "field": "WhatId",
      "junctionIdListNames": [],
      "junctionReferenceTo": [],
      "relationshipName": "Tasks",
      "restrictedDelete": false
    },
    {
      "cascadeDelete": false,
      "childSObject": "TaskChangeEvent",
      "deprecatedAndHidden": false,
      "field": "WhatId",
      "junctionIdListNames": [],
      "junctionReferenceTo": [],
      "relationshipName": null,
      "restrictedDelete": false
    },
    {
      "cascadeDelete": true,
      "childSObject": "TaskRelation",
      "deprecatedAndHidden": false,
      "field": "RelationId",
      "junctionIdListNames": [],
      "junctionReferenceTo": [],
      "relationshipName": "TaskRelations",
      "restrictedDelete": false
    },
    {
      "cascadeDelete": false,
      "childSObject": "TaskRelationChangeEvent",
      "deprecatedAndHidden": false,
      "field": "RelationId",
      "junctionIdListNames": [],
      "junctionReferenceTo": [],
      "relationshipName": null,
      "restrictedDelete": false
    },
    {
      "cascadeDelete": false,
      "childSObject": "WorkOrderLineItem",
      "deprecatedAndHidden": false,
      "field": "Product2Id",
      "junctionIdListNames": [],
      "junctionReferenceTo": [],
      "relationshipName": "WorkOrderLineItems",
      "restrictedDelete": false
    },
    {
      "cascadeDelete": false,
      "childSObject": "WorkOrderLineItemChangeEvent",
      "deprecatedAndHidden": false,
      "field": "Product2Id",
      "junctionIdListNames": [],
      "junctionReferenceTo": [],
      "relationshipName": null,
      "restrictedDelete": false
    },
    {
      "cascadeDelete": false,
      "childSObject": "WorkPlanSelectionRule",
      "deprecatedAndHidden": false,
      "field": "Product2Id",
      "junctionIdListNames": [],
      "junctionReferenceTo": [],
      "relationshipName": "WorkPlanSelectionRules",
      "restrictedDelete": false
    },
    {
      "cascadeDelete": false,
      "childSObject": "WorkPlanSelectionRuleChangeEvent",
      "deprecatedAndHidden": false,
      "field": "Product2Id",
      "junctionIdListNames": [],
      "junctionReferenceTo": [],
      "relationshipName": null,
      "restrictedDelete": false
    },
    {
      "cascadeDelete": false,
      "childSObject": "vlocity_cmt__AccountDiscountItem__c",
      "deprecatedAndHidden": false,
      "field": "vlocity_cmt__ProductId__c",
      "junctionIdListNames": [],
      "junctionReferenceTo": [],
      "relationshipName": "vlocity_cmt__AccountDiscountItemsProduct__r",
      "restrictedDelete": false
    },
    {
      "cascadeDelete": false,
      "childSObject": "vlocity_cmt__AccountOffer__c",
      "deprecatedAndHidden": false,
      "field": "vlocity_cmt__ProductId__c",
      "junctionIdListNames": [],
      "junctionReferenceTo": [],
      "relationshipName": "vlocity_cmt__Offers__r",
      "restrictedDelete": false
    },
    {
      "cascadeDelete": false,
      "childSObject": "vlocity_cmt__AccountProductRollup__c",
      "deprecatedAndHidden": false,
      "field": "vlocity_cmt__ProductId__c",
      "junctionIdListNames": [],
      "junctionReferenceTo": [],
      "relationshipName": "vlocity_cmt__AccountProductRollups__r",
      "restrictedDelete": false
    },
    {
      "cascadeDelete": false,
      "childSObject": "vlocity_cmt__AdSpaceSpecification__c",
      "deprecatedAndHidden": false,
      "field": "vlocity_cmt__Product2Id__c",
      "junctionIdListNames": [],
      "junctionReferenceTo": [],
      "relationshipName": "vlocity_cmt__AdSpaceSpecifications__r",
      "restrictedDelete": false
    },
    {
      "cascadeDelete": false,
      "childSObject": "vlocity_cmt__Application__c",
      "deprecatedAndHidden": false,
      "field": "vlocity_cmt__Product2Id__c",
      "junctionIdListNames": [],
      "junctionReferenceTo": [],
      "relationshipName": "vlocity_cmt__Applications__r",
      "restrictedDelete": false
    },
    {
      "cascadeDelete": false,
      "childSObject": "vlocity_cmt__BusinessSiteOffering__c",
      "deprecatedAndHidden": false,
      "field": "vlocity_cmt__ProductId__c",
      "junctionIdListNames": [],
      "junctionReferenceTo": [],
      "relationshipName": "vlocity_cmt__SiteServicesProducts__r",
      "restrictedDelete": false
    },
    {
      "cascadeDelete": false,
      "childSObject": "vlocity_cmt__CachedFilterableAttribute__c",
      "deprecatedAndHidden": false,
      "field": "vlocity_cmt__Product2Id__c",
      "junctionIdListNames": [],
      "junctionReferenceTo": [],
      "relationshipName": "vlocity_cmt__CachedFilterableAttribute__r",
      "restrictedDelete": false
    },
    {
      "cascadeDelete": false,
      "childSObject": "vlocity_cmt__CachedProduct2Translation__c",
      "deprecatedAndHidden": false,
      "field": "vlocity_cmt__Product2Id__c",
      "junctionIdListNames": [],
      "junctionReferenceTo": [],
      "relationshipName": "vlocity_cmt__Cached_Product2_Translations__r",
      "restrictedDelete": false
    },
    {
      "cascadeDelete": false,
      "childSObject": "vlocity_cmt__CartItem__c",
      "deprecatedAndHidden": false,
      "field": "vlocity_cmt__Product2Id__c",
      "junctionIdListNames": [],
      "junctionReferenceTo": [],
      "relationshipName": "vlocity_cmt__CartItemsProduct__r",
      "restrictedDelete": false
    },
    {
      "cascadeDelete": false,
      "childSObject": "vlocity_cmt__CatalogProductRelationship__c",
      "deprecatedAndHidden": false,
      "field": "vlocity_cmt__Product2Id__c",
      "junctionIdListNames": [],
      "junctionReferenceTo": [],
      "relationshipName": "vlocity_cmt__CatalogProductRelationships2__r",
      "restrictedDelete": false
    },
    {
      "cascadeDelete": false,
      "childSObject": "vlocity_cmt__CompiledAttributeOverride__c",
      "deprecatedAndHidden": false,
      "field": "vlocity_cmt__ProductId__c",
      "junctionIdListNames": [],
      "junctionReferenceTo": [],
      "relationshipName": "vlocity_cmt__CompiledAttributeOverrides__r",
      "restrictedDelete": false
    },
    {
      "cascadeDelete": false,
      "childSObject": "vlocity_cmt__ContractLineItem__c",
      "deprecatedAndHidden": false,
      "field": "vlocity_cmt__Product2Id__c",
      "junctionIdListNames": [],
      "junctionReferenceTo": [],
      "relationshipName": "vlocity_cmt__OrderProduct__r",
      "restrictedDelete": false
    },
    {
      "cascadeDelete": false,
      "childSObject": "vlocity_cmt__ContractLineItem__c",
      "deprecatedAndHidden": false,
      "field": "vlocity_cmt__ProductId__c",
      "junctionIdListNames": [],
      "junctionReferenceTo": [],
      "relationshipName": "vlocity_cmt__GroupBenefitsPlans__r",
      "restrictedDelete": false
    },
    {
      "cascadeDelete": false,
      "childSObject": "vlocity_cmt__ContractTerm__c",
      "deprecatedAndHidden": false,
      "field": "vlocity_cmt__TermSpecProduct2Id__c",
      "junctionIdListNames": [],
      "junctionReferenceTo": [],
      "relationshipName": "vlocity_cmt__ContractTerms__r",
      "restrictedDelete": false
    },
    {
      "cascadeDelete": false,
      "childSObject": "vlocity_cmt__ContractTypeTerm__c",
      "deprecatedAndHidden": false,
      "field": "vlocity_cmt__TermSpecProduct2Id__c",
      "junctionIdListNames": [],
      "junctionReferenceTo": [],
      "relationshipName": "vlocity_cmt__ContractTypeTerms__r",
      "restrictedDelete": false
    },
    {
      "cascadeDelete": false,
      "childSObject": "vlocity_cmt__ContractVersionDiscountItem__c",
      "deprecatedAndHidden": false,
      "field": "vlocity_cmt__ProductId__c",
      "junctionIdListNames": [],
      "junctionReferenceTo": [],
      "relationshipName": "vlocity_cmt__ContractVersionDiscountItemsProduct__r",
      "restrictedDelete": false
    },
    {
      "cascadeDelete": false,
      "childSObject": "vlocity_cmt__Datastore__c",
      "deprecatedAndHidden": false,
      "field": "vlocity_cmt__ProductId__c",
      "junctionIdListNames": [],
      "junctionReferenceTo": [],
      "relationshipName": "vlocity_cmt__DataStoreItems__r",
      "restrictedDelete": false
    },
    {
      "cascadeDelete": false,
      "childSObject": "vlocity_cmt__DecompositionRelationship__c",
      "deprecatedAndHidden": false,
      "field": "vlocity_cmt__DestinationProductId__c",
      "junctionIdListNames": [],
      "junctionReferenceTo": [],
      "relationshipName": "vlocity_cmt__SourceDecompositionRelationships__r",
      "restrictedDelete": false
    },
    {
      "cascadeDelete": false,
      "childSObject": "vlocity_cmt__DecompositionRelationship__c",
      "deprecatedAndHidden": false,
      "field": "vlocity_cmt__SourceProductId__c",
      "junctionIdListNames": [],
      "junctionReferenceTo": [],
      "relationshipName": "vlocity_cmt__DestinationDecompositionRelationships__r",
      "restrictedDelete": false
    },
    {
      "cascadeDelete": false,
      "childSObject": "vlocity_cmt__DocumentTemplateSectionCondition__c",
      "deprecatedAndHidden": false,
      "field": "vlocity_cmt__Product2Id__c",
      "junctionIdListNames": [],
      "junctionReferenceTo": [],
      "relationshipName": "vlocity_cmt__DocumentTemplateSectionConditions__r",
      "restrictedDelete": false
    },
    {
      "cascadeDelete": false,
      "childSObject": "vlocity_cmt__EntityFilterMember__c",
      "deprecatedAndHidden": false,
      "field": "vlocity_cmt__ProductId__c",
      "junctionIdListNames": [],
      "junctionReferenceTo": [],
      "relationshipName": "vlocity_cmt__EntityFilterMembers__r",
      "restrictedDelete": false
    },
    {
      "cascadeDelete": false,
      "childSObject": "vlocity_cmt__FulfilmentRequestLine__c",
      "deprecatedAndHidden": false,
      "field": "vlocity_cmt__Product2Id__c",
      "junctionIdListNames": [],
      "junctionReferenceTo": [],
      "relationshipName": "vlocity_cmt__FulfillmentRequestLines__r",
      "restrictedDelete": false
    },
    {
      "cascadeDelete": false,
      "childSObject": "vlocity_cmt__InventoryItem__c",
      "deprecatedAndHidden": false,
      "field": "vlocity_cmt__ProductId__c",
      "junctionIdListNames": [],
      "junctionReferenceTo": [],
      "relationshipName": "vlocity_cmt__InventoryItems__r",
      "restrictedDelete": false
    },
    {
      "cascadeDelete": false,
      "childSObject": "vlocity_cmt__OfferMigrationComponentMapping__c",
      "deprecatedAndHidden": false,
      "field": "vlocity_cmt__SourceProductId__c",
      "junctionIdListNames": [],
      "junctionReferenceTo": [],
      "relationshipName": "vlocity_cmt__SourceProductId__r",
      "restrictedDelete": false
    },
    {
      "cascadeDelete": false,
      "childSObject": "vlocity_cmt__OfferMigrationComponentMapping__c",
      "deprecatedAndHidden": false,
      "field": "vlocity_cmt__TargetProductId__c",
      "junctionIdListNames": [],
      "junctionReferenceTo": [],
      "relationshipName": "vlocity_cmt__TargetProductId__r",
      "restrictedDelete": false
    },
    {
      "cascadeDelete": false,
      "childSObject": "vlocity_cmt__OfferPricingComponent__c",
      "deprecatedAndHidden": false,
      "field": "vlocity_cmt__OfferId__c",
      "junctionIdListNames": [],
      "junctionReferenceTo": [],
      "relationshipName": "vlocity_cmt__OfferPricingComponents__r",
      "restrictedDelete": false
    },
    {
      "cascadeDelete": false,
      "childSObject": "vlocity_cmt__OfferPricingComponent__c",
      "deprecatedAndHidden": false,
      "field": "vlocity_cmt__RootOfferId__c",
      "junctionIdListNames": [],
      "junctionReferenceTo": [],
      "relationshipName": "vlocity_cmt__RootOfferPricingComponents__r",
      "restrictedDelete": false
    },
    {
      "cascadeDelete": false,
      "childSObject": "vlocity_cmt__OpportunityDiscountItem__c",
      "deprecatedAndHidden": false,
      "field": "vlocity_cmt__ProductId__c",
      "junctionIdListNames": [],
      "junctionReferenceTo": [],
      "relationshipName": "vlocity_cmt__OpportunityDiscountItems__r",
      "restrictedDelete": false
    },
    {
      "cascadeDelete": false,
      "childSObject": "vlocity_cmt__OrchestrationQueueAssignmentRule__c",
      "deprecatedAndHidden": false,
      "field": "vlocity_cmt__Product2Id__c",
      "junctionIdListNames": [],
      "junctionReferenceTo": [],
      "relationshipName": "vlocity_cmt__OrchestrationQueueAssignmentRules__r",
      "restrictedDelete": false
    },
    {
      "cascadeDelete": false,
      "childSObject": "vlocity_cmt__OrchestrationScenario__c",
      "deprecatedAndHidden": false,
      "field": "vlocity_cmt__Product2Id__c",
      "junctionIdListNames": [],
      "junctionReferenceTo": [],
      "relationshipName": "vlocity_cmt__OrchestrationScenarios__r",
      "restrictedDelete": false
    },
    {
      "cascadeDelete": false,
      "childSObject": "vlocity_cmt__OrderDiscountItem__c",
      "deprecatedAndHidden": false,
      "field": "vlocity_cmt__ProductId__c",
      "junctionIdListNames": [],
      "junctionReferenceTo": [],
      "relationshipName": "vlocity_cmt__OrderDiscountItems__r",
      "restrictedDelete": false
    },
    {
      "cascadeDelete": false,
      "childSObject": "vlocity_cmt__OrderProductRollup__c",
      "deprecatedAndHidden": false,
      "field": "vlocity_cmt__ProductId__c",
      "junctionIdListNames": [],
      "junctionReferenceTo": [],
      "relationshipName": "vlocity_cmt__OrderProductRollups__r",
      "restrictedDelete": false
    },
    {
      "cascadeDelete": false,
      "childSObject": "vlocity_cmt__OverrideDefinition__c",
      "deprecatedAndHidden": false,
      "field": "vlocity_cmt__ProductId__c",
      "junctionIdListNames": [],
      "junctionReferenceTo": [],
      "relationshipName": "vlocity_cmt__OverrideDefinitions__r",
      "restrictedDelete": false
    },
    {
      "cascadeDelete": false,
      "childSObject": "vlocity_cmt__PriceListEntry__c",
      "deprecatedAndHidden": false,
      "field": "vlocity_cmt__OfferId__c",
      "junctionIdListNames": [],
      "junctionReferenceTo": [],
      "relationshipName": "vlocity_cmt__PriceListEntries__r",
      "restrictedDelete": false
    },
    {
      "cascadeDelete": false,
      "childSObject": "vlocity_cmt__PriceListEntry__c",
      "deprecatedAndHidden": false,
      "field": "vlocity_cmt__ProductId__c",
      "junctionIdListNames": [],
      "junctionReferenceTo": [],
      "relationshipName": "vlocity_cmt__ProductPriceListEntries__r",
      "restrictedDelete": false
    },
    {
      "cascadeDelete": false,
      "childSObject": "vlocity_cmt__PricingElement__c",
      "deprecatedAndHidden": false,
      "field": "vlocity_cmt__OfferId__c",
      "junctionIdListNames": [],
      "junctionReferenceTo": [],
      "relationshipName": "vlocity_cmt__OfferPricingElements__r",
      "restrictedDelete": false
    },
    {
      "cascadeDelete": false,
      "childSObject": "vlocity_cmt__PricingElement__c",
      "deprecatedAndHidden": false,
      "field": "vlocity_cmt__ProductId__c",
      "junctionIdListNames": [],
      "junctionReferenceTo": [],
      "relationshipName": "vlocity_cmt__PricingElements__r",
      "restrictedDelete": false
    },
    {
      "cascadeDelete": false,
      "childSObject": "vlocity_cmt__ProductAvailability__c",
      "deprecatedAndHidden": false,
      "field": "vlocity_cmt__Product2Id__c",
      "junctionIdListNames": [],
      "junctionReferenceTo": [],
      "relationshipName": "vlocity_cmt__ProductEligibility__r",
      "restrictedDelete": false
    },
    {
      "cascadeDelete": false,
      "childSObject": "vlocity_cmt__ProductChildItem__c",
      "deprecatedAndHidden": false,
      "field": "vlocity_cmt__ChildProductId__c",
      "junctionIdListNames": [],
      "junctionReferenceTo": [],
      "relationshipName": "vlocity_cmt__ProductChildItemsChild__r",
      "restrictedDelete": false
    },
    {
      "cascadeDelete": false,
      "childSObject": "vlocity_cmt__ProductChildItem__c",
      "deprecatedAndHidden": false,
      "field": "vlocity_cmt__ParentProductId__c",
      "junctionIdListNames": [],
      "junctionReferenceTo": [],
      "relationshipName": "vlocity_cmt__ProductChildItems__r",
      "restrictedDelete": false
    },
    {
      "cascadeDelete": false,
      "childSObject": "vlocity_cmt__ProductConfigurationProcedure__c",
      "deprecatedAndHidden": false,
      "field": "vlocity_cmt__ProductId__c",
      "junctionIdListNames": [],
      "junctionReferenceTo": [],
      "relationshipName": "vlocity_cmt__ProductConfigurationProcedures__r",
      "restrictedDelete": false
    },
    {
      "cascadeDelete": false,
      "childSObject": "vlocity_cmt__ProductEligibility__c",
      "deprecatedAndHidden": false,
      "field": "vlocity_cmt__Product2Id__c",
      "junctionIdListNames": [],
      "junctionReferenceTo": [],
      "relationshipName": "vlocity_cmt__ProductEligibilityProduct__r",
      "restrictedDelete": false
    },
    {
      "cascadeDelete": false,
      "childSObject": "vlocity_cmt__ProductRelationship__c",
      "deprecatedAndHidden": false,
      "field": "vlocity_cmt__Product2Id__c",
      "junctionIdListNames": [],
      "junctionReferenceTo": [],
      "relationshipName": "vlocity_cmt__RelatedProduct__r",
      "restrictedDelete": false
    },
    {
      "cascadeDelete": false,
      "childSObject": "vlocity_cmt__ProductRelationship__c",
      "deprecatedAndHidden": false,
      "field": "vlocity_cmt__RelatedProductId__c",
      "junctionIdListNames": [],
      "junctionReferenceTo": [],
      "relationshipName": "vlocity_cmt__ProductRelations1__r",
      "restrictedDelete": false
    },
    {
      "cascadeDelete": false,
      "childSObject": "vlocity_cmt__PromotionApplicableProduct__c",
      "deprecatedAndHidden": false,
      "field": "vlocity_cmt__ContextOfferId__c",
      "junctionIdListNames": [],
      "junctionReferenceTo": [],
      "relationshipName": "vlocity_cmt__PromotionApplicableProductContext__r",
      "restrictedDelete": false
    },
    {
      "cascadeDelete": false,
      "childSObject": "vlocity_cmt__PromotionApplicableProduct__c",
      "deprecatedAndHidden": false,
      "field": "vlocity_cmt__ProductId__c",
      "junctionIdListNames": [],
      "junctionReferenceTo": [],
      "relationshipName": "vlocity_cmt__PromotionApplicableProduct__r",
      "restrictedDelete": false
    },
    {
      "cascadeDelete": false,
      "childSObject": "vlocity_cmt__PromotionIncludedProduct__c",
      "deprecatedAndHidden": false,
      "field": "vlocity_cmt__ProductId__c",
      "junctionIdListNames": [],
      "junctionReferenceTo": [],
      "relationshipName": "vlocity_cmt__PromotionIncludedProducts__r",
      "restrictedDelete": false
    },
    {
      "cascadeDelete": false,
      "childSObject": "vlocity_cmt__PromotionItem__c",
      "deprecatedAndHidden": false,
      "field": "vlocity_cmt__ContextProductId__c",
      "junctionIdListNames": [],
      "junctionReferenceTo": [],
      "relationshipName": "vlocity_cmt__ContextPromotionItems__r",
      "restrictedDelete": false
    },
    {
      "cascadeDelete": false,
      "childSObject": "vlocity_cmt__PromotionItem__c",
      "deprecatedAndHidden": false,
      "field": "vlocity_cmt__OfferId__c",
      "junctionIdListNames": [],
      "junctionReferenceTo": [],
      "relationshipName": "vlocity_cmt__OfferPromotionItems__r",
      "restrictedDelete": false
    },
    {
      "cascadeDelete": false,
      "childSObject": "vlocity_cmt__PromotionItem__c",
      "deprecatedAndHidden": false,
      "field": "vlocity_cmt__ProductId__c",
      "junctionIdListNames": [],
      "junctionReferenceTo": [],
      "relationshipName": "vlocity_cmt__PromotionItems__r",
      "restrictedDelete": false
    },
    {
      "cascadeDelete": false,
      "childSObject": "vlocity_cmt__QuoteDiscountItem__c",
      "deprecatedAndHidden": false,
      "field": "vlocity_cmt__ProductId__c",
      "junctionIdListNames": [],
      "junctionReferenceTo": [],
      "relationshipName": "vlocity_cmt__QuoteDiscountItemsProduct__r",
      "restrictedDelete": false
    },
    {
      "cascadeDelete": false,
      "childSObject": "vlocity_cmt__QuoteProductRollup__c",
      "deprecatedAndHidden": false,
      "field": "vlocity_cmt__ProductId__c",
      "junctionIdListNames": [],
      "junctionReferenceTo": [],
      "relationshipName": "vlocity_cmt__QuoteProductRollups__r",
      "restrictedDelete": false
    },
    {
      "cascadeDelete": false,
      "childSObject": "vlocity_cmt__SpecTemplateMapping__c",
      "deprecatedAndHidden": false,
      "field": "vlocity_cmt__TemplateProductId__c",
      "junctionIdListNames": [],
      "junctionReferenceTo": [],
      "relationshipName": "vlocity_cmt__SpecTemplateMappings__r",
      "restrictedDelete": false
    },
    {
      "cascadeDelete": false,
      "childSObject": "vlocity_cmt__VlocityTrackingEntry__c",
      "deprecatedAndHidden": false,
      "field": "vlocity_cmt__ProductId__c",
      "junctionIdListNames": [],
      "junctionReferenceTo": [],
      "relationshipName": "vlocity_cmt__TrackingEntries__r",
      "restrictedDelete": false
    },
    {
      "cascadeDelete": false,
      "childSObject": "vlocity_cmt__VqResource__c",
      "deprecatedAndHidden": false,
      "field": "vlocity_cmt__LinkedProductId__c",
      "junctionIdListNames": [],
      "junctionReferenceTo": [],
      "relationshipName": "vlocity_cmt__Vlocity_Intelligence_Resources__r",
      "restrictedDelete": false
    }
  ],
  "custom": false,
  "name": "Product2",
  "queryable": true
}